ase_weas_widget/__about__.py
ase_weas_widget/__init__.py
ase_weas_widget/registry.py
ase_weas_widget/viewer.py
ase_weas_widget-0.2.0.dist-info/METADATA
ase_weas_widget-0.2.0.dist-info/WHEEL
ase_weas_widget-0.2.0.dist-info/entry_points.txt
ase_weas_widget-0.2.0.dist-info/licenses/LICENSE.txt
ase_weas_widget-0.2.0.dist-info/RECORD
