Metadata-Version: 2.4
Name: ase-weas-widget
Version: 0.2.0
Summary: Visualizer plugin to use ase with weas-widget
Project-URL: Documentation, https://github.com/zhubonan/ase-weas-widget#readme
Project-URL: Issues, https://github.com/zhubonan/ase-weas-widget/issues
Project-URL: Source, https://github.com/zhubonan/ase-weas-widget
Author-email: Bonan Zhu <zhubonan@outlook.com>
License-Expression: MIT
License-File: LICENSE.txt
Classifier: Development Status :: 4 - Beta
Classifier: Programming Language :: Python
Classifier: Programming Language :: Python :: 3.8
Classifier: Programming Language :: Python :: 3.9
Classifier: Programming Language :: Python :: 3.10
Classifier: Programming Language :: Python :: 3.11
Classifier: Programming Language :: Python :: 3.12
Classifier: Programming Language :: Python :: Implementation :: CPython
Classifier: Programming Language :: Python :: Implementation :: PyPy
Requires-Python: >=3.8
Requires-Dist: ase>=3.24
Requires-Dist: weas-widget
